fastmodel/__init__.py
fastmodel/main.py
fastmodel/backend/__init__.py
fastmodel/backend/constant/__init__.py
fastmodel/backend/constant/biz_constants.py
fastmodel/backend/domain/__init__.py
fastmodel/backend/domain/dto/__init__.py
fastmodel/backend/domain/dto/req_classes.py
fastmodel/backend/domain/dto/rsp_classes.py
fastmodel/backend/exception/__init__.py
fastmodel/backend/exception/exceptions.py
fastmodel/backend/inference/__init__.py
fastmodel/backend/inference/inference.py
fastmodel/backend/process/__init__.py
fastmodel/backend/process/cv_process.py
fastmodel/backend/util/__init__.py
fastmodel/backend/util/file.py
fastmodel/backend/util/img_util.py
fastmodel/backend/util/str_util.py
fastmodel/frontend/__init__.py
fastmodel/frontend/edit-anything/index.html
fastmodel/frontend/edit-anything/assets/css/801e8f75.css
fastmodel/frontend/edit-anything/assets/css/db720fc8.css
fastmodel/frontend/edit-anything/assets/img/favicon.ico
fastmodel/frontend/edit-anything/assets/img/low-salary.de80db91.jpg
fastmodel/frontend/edit-anything/js/764.d32bc368.js
fastmodel/frontend/edit-anything/js/764.d32bc368.js.LICENSE.txt
fastmodel/frontend/edit-anything/js/antd.a691f5d1.js
fastmodel/frontend/edit-anything/js/main.7d537378.js
fastmodel/frontend/edit-anything/js/runtime~main.0144593e.js
fastmodel/frontend/edit-anything/tmp/img/in/a.txt
fastmodel/frontend/edit-anything/tmp/img/out/a.txt
edit_anything-0.0.5.dist-info/METADATA
edit_anything-0.0.5.dist-info/WHEEL
edit_anything-0.0.5.dist-info/entry_points.txt
edit_anything-0.0.5.dist-info/top_level.txt
edit_anything-0.0.5.dist-info/RECORD
