Metadata-Version: 2.1
Name: edit-anything
Version: 0.0.5
Summary: EditAnything
Home-page: https://github.com/xxx/xxxx
Author: edit-anything
Author-email: edit-anything@openmmlab.com
License: Apache License 2.0
Keywords: EditAnything
Platform: UNKNOWN
Classifier: Development Status :: 3 - Alpha
Requires-Dist: fastapi (==0.95.1)
Requires-Dist: uvicorn[standard] (==0.22.0)
Requires-Dist: pydantic (==1.10.7)
Requires-Dist: starlette (==0.26.1)
Requires-Dist: diffusers
Requires-Dist: transformers
Requires-Dist: accelerate
Requires-Dist: scipy
Requires-Dist: safetensors
